{
	"questions": [
		{
			"author": "Maxence",
			"round": "FIRST_ROUND",
			"statement": "How many languages are spoken in Belgium ?",
			"choices": {
				"1": false,
				"2": false,
				"3": true,
				"4": false
			}
		},
		{
			"author": "Maxence",
			"round": "SECOND_ROUND",
			"statement": "What is the capital of the United States ?",
			"choices": {
				"New York": false,
				"Hollywood": false,
				"Las Vegas": false,
				"Washington B.C.": true
			}
		},
		{
			"author": "Maxence",
			"round": "LAST_ROUND",
			"statement": "How far is the Earth away from the Sun in miles ?",
			"choices": {
				"9,3 million": false,
				"193 million": false,
				"93 million": true,
				"39 million": false
			}
		},
		{
			"author": "David-E.",
			"round": "FIRST_ROUND",
			"statement": "What was Donald J. Trump\u0027s slogan during his 2016 campaign ?",
			"choices": {
				"I love chocolat !": false,
				"Make America great again !": true,
				"We will build a wall !": false,
				"Want to do a ride ?": false
			}
		},
		{
			"author": "David-E.",
			"round": "SECOND_ROUND",
			"statement": "During the 2016-2017 season, which football team won the Champions League? ",
			"choices": {
				"FC Barcelona": false,
				"Real Madrid": true,
				"Juventus of Turin": false,
				"Bayern of Munich": false
			}
		},
		{
			"author": "David-E.",
			"round": "LAST_ROUND",
			"statement": "What\u0027s a Verbicrucist ?",
			"choices": {
				"A person who forms new words": false,
				"A person who studies the origin of words": false,
				"A person who updates the dictionary": false,
				"A person who develops crossword puzzles": true
			}
		},
		{
			"author": "Anthony",
			"round": "FIRST_ROUND",
			"statement": "What is the smallest unit in a computer\u0027s memory ?",
			"choices": {
				"Byte": false,
				"Dot": false,
				"Bit": true,
				"Foot": false
			}
		},
		{
			"author": "Anthony",
			"round": "SECOND_ROUND",
			"statement": "Who was Bonnie\u0027s famous partner in crime ?",
			"choices": {
				"Captain Haddock": false,
				"Clyde": true,
				"Snowy": false,
				"Robin Hood": false
			}
		},
		{
			"author": "Anthony",
			"round": "LAST_ROUND",
			"statement": "How far is Earth from the Sun ?",
			"choices": {
				"93 million miles": true,
				"9.3 million kilometres": false,
				"93 million kilometres": false,
				"9.3 million miles": false
			}
		}
	]
}